MANIFEST.in
requirements.txt
setup.py
concord/__init__.py
concord/concord_entry.py
concord/config.py
concord/constants.py
concord/dcos_utils.py
concord/deploy.py
concord/functional_utils.py
concord/kill_task.py
concord/marathon.py
concord/print_graph.py
concord/runway.py
concord/thrift_utils.py
concord/utils.py
concord.egg-info/PKG-INFO
concord.egg-info/SOURCES.txt
concord.egg-info/dependency_links.txt
concord.egg-info/entry_points.txt
concord.egg-info/requires.txt
concord.egg-info/top_level.txt
concord/internal/__init__.py
concord/internal/thrift/BoltManagerService.py
concord/internal/thrift/BoltMetricsService.py
concord/internal/thrift/BoltPipeService.py
concord/internal/thrift/BoltProxyService.py
concord/internal/thrift/BoltSchedulerService.py
concord/internal/thrift/ComputationService.py
concord/internal/thrift/MutableEphemeralStateService.py
concord/internal/thrift/__init__.py
concord/internal/thrift/constants.py
concord/internal/thrift/ttypes.py
concord/resources/config_schema.json