Metadata-Version: 1.1
Name: concord
Version: 0.2.9
Summary: python concord command line tools
Home-page: https://github.com/concord/cmd
Author: Concord Systems
Author-email: support@concord.io
License: UNKNOWN
Keywords: dcos mesos streams operator
Platform: UNKNOWN
Classifier: Development Status :: 3 - Alpha
Classifier: Intended Audience :: Developers
Classifier: Intended Audience :: Information Technology
Classifier: Programming Language :: Python :: 2.7
